solutions/hw2_q2_dut.vhdl
library IEEE;
use IEEE.STD_LOGIC_1164.ALL;
entity dut is
    Generic ( param : integer range 0 to 63 := 5);
    Port ( signal_in : in  std_logic;
    		  enable : in  std_logic;
    		  clk : in std_logic;
           signal_out : out  std_logic);
end dut;
architecture Behavioral of dut is
	signal ctr : integer range 0 to 63 := 0;
	signal out_reg : std_logic := '0';
	constant maxctr : integer range 0 to 63 := param;
begin
	debounce_process : process (clk)
	begin
	   if (rising_edge(clk)) then
	      if (ctr = maxctr) then
	         out_reg <= not(out_reg);
	      end if;
	   end if;
	end process;
	counter_process : process (clk)
	begin
		if (rising_edge(clk)) then
			if ((out_reg = '1') xor (signal_in = '1')) then
				if (ctr = maxctr) then
					ctr <= 0;
				else
					ctr <= ctr + 1;
				end if;
			else
				ctr <= 0;
			end if;
		end if;
	end process;
	enable_process : process (clk, signal_in, out_reg)
	begin
		if(enable = '1') then
			signal_out <= out_reg;
		else
			signal_out <= signal_in;
		end if;
	end process;
end Behavioral;

content/hw2_q2_dut_tb.vhdl
library IEEE;
use IEEE.STD_LOGIC_1164.ALL;
entity dut_tb is
end dut_tb;
architecture Behavioral of dut_tb is
    component dut
        Generic ( param : integer);
        Port ( signal_in : in  std_logic;
               enable : in std_logic; 
               clk : in  std_logic;
               signal_out : out  std_logic);
    end component;
    signal signal_in_tb : std_logic := '0';
    signal enable_tb : std_logic := '0';
    signal clk_tb : std_logic := '0';
    signal signal_out_tb : std_logic := '0';
    constant param_tb : integer := 4;
begin
    dut_module: dut
            generic map(param => param_tb)
            port map(signal_in => signal_in_tb, signal_out => signal_out_tb, clk => clk_tb, enable => enable_tb);
    clk_process : process
    begin
        clk_tb <= '1';
        wait for 5 ns;
        clk_tb <= '0';
        wait for 5 ns;
    end process;
    sim_process : process
    begin
        assert false report "Running testbench" severity note;
    
        wait for 5 ns; -- offset everything to see rising edges clearly
        enable_tb <= '0';
        signal_in_tb <= '0';
        wait for 10 ns; -- 15ns
        assert signal_in_tb = signal_out_tb report "Should have gotten signal_in_tb = signal_out_tb by now, but it didn't happen" severity failure;
        wait for 40 ns; -- 55ns
        signal_in_tb <= '1';
        wait for 10 ns; -- 65ns
        assert signal_in_tb = signal_out_tb report "Should have gotten signal_in_tb = signal_out_tb by now, but it didn't happen" severity failure;
        wait for 40 ns; -- 105ns
        signal_in_tb <= '0';
        wait for 10 ns; -- 115ns
        assert signal_in_tb = signal_out_tb report "Should have gotten signal_in_tb = signal_out_tb by now, but it didn't happen" severity failure;
        wait for 40 ns; -- 155ns
        enable_tb <= '1';
        signal_in_tb <= '1'; 
        wait for 10 ns; -- 165ns
        assert signal_out_tb = '0' report "Should have gotten signal_out_tb = 0 by now, but it didn't happen" severity failure;
        signal_in_tb <= '0'; 
        wait for 10 ns; -- 175ns 
        assert signal_out_tb = '0' report "Should have gotten signal_out_tb = 0 by now, but it didn't happen" severity failure;
        signal_in_tb <= '1';
        wait for 55 ns; -- 230ns
        assert signal_out_tb = '1' report "Should have gotten signal_out_tb = 1 by now, but it didn't happen" severity failure;
        wait for 5 ns; -- 235ns
        signal_in_tb <= '0';
        wait for 55 ns; -- 290ns
        assert signal_out_tb = '0' report "Should have gotten signal_out_tb = 0 by now, but it didn't happen" severity failure;
        wait for 5 ns; -- 295ns
        wait;
    end process;
end Behavioral;

content/hw2_q2_dut_tb_refout.vcd
$date
  Wed Nov 27 21:16:54 2024
$end
$version
  GHDL v0
$end
$timescale
  1 fs
$end
$scope module standard $end
$upscope $end
$scope module std_logic_1164 $end
$upscope $end
$scope module dut_tb $end
$var reg 1 ! signal_in_tb $end
$var reg 1 " enable_tb $end
$var reg 1 # clk_tb $end
$var reg 1 $ signal_out_tb $end
$scope module dut_module $end
$var reg 1 % signal_in $end
$var reg 1 & enable $end
$var reg 1 ' clk $end
$var reg 1 ( signal_out $end
$var integer 32 ) ctr $end
$var reg 1 * out_reg $end
$upscope $end
$upscope $end
$enddefinitions $end
#0
0!
0"
1#
0$
0%
0&
1'
0(
b0 )
0*
#5000000
0#
0'
#10000000
1#
1'
#15000000
0#
0'
#20000000
1#
1'
#25000000
0#
0'
#30000000
1#
1'
#35000000
0#
0'
#40000000
1#
1'
#45000000
0#
0'
#50000000
1#
1'
#55000000
1!
0#
1$
1%
0'
1(
#60000000
1#
1'
b1 )
#65000000
0#
0'
#70000000
1#
1'
b10 )
#75000000
0#
0'
#80000000
1#
1'
b11 )
#85000000
0#
0'
#90000000
1#
1'
b100 )
#95000000
0#
0'
#100000000
1#
1'
b0 )
1*
#105000000
0!
0#
0$
0%
0'
0(
#110000000
1#
1'
b1 )
#115000000
0#
0'
#120000000
1#
1'
b10 )
#125000000
0#
0'
#130000000
1#
1'
b11 )
#135000000
0#
0'
#140000000
1#
1'
b100 )
#145000000
0#
0'
#150000000
1#
1'
b0 )
0*
#155000000
1!
1"
0#
1%
1&
0'
#160000000
1#
1'
b1 )
#165000000
0!
0#
0%
0'
#170000000
1#
1'
b0 )
#175000000
1!
0#
1%
0'
#180000000
1#
1'
b1 )
#185000000
0#
0'
#190000000
1#
1'
b10 )
#195000000
0#
0'
#200000000
1#
1'
b11 )
#205000000
0#
0'
#210000000
1#
1'
b100 )
#215000000
0#
0'
#220000000
1#
1$
1'
1(
b0 )
1*
#225000000
0#
0'
#230000000
1#
1'
#235000000
0!
0#
0%
0'
#240000000
1#
1'
b1 )
#245000000
0#
0'
#250000000
1#
1'
b10 )
#255000000
0#
0'
#260000000
1#
1'
b11 )
#265000000
0#
0'
#270000000
1#
1'
b100 )
#275000000
0#
0'
#280000000
1#
0$
1'
0(
b0 )
0*
