solutions/hw2_q3_dut.vhdl
library IEEE;
use IEEE.STD_LOGIC_1164.ALL;
entity dut is
	Generic ( param_up : integer range 0 to 63 := 5;
			  param_down : integer range 0 to 63 := 5);
	Port (	signal_in : in  std_logic;
		clk : in std_logic;
		signal_out : out  std_logic);
end dut;
architecture Behavioral of dut is
	signal ctr : integer range 0 to 63 := 0;
	signal out_reg : std_logic := '0';
	constant maxctr_up : integer range 0 to 63 := param_up;
	constant maxctr_down : integer range 0 to 63 := param_down;
	signal maxctr : integer := param_up;
begin
	debounce_process : process (clk)
	begin
	if (rising_edge(clk)) then
		if (ctr = maxctr) then
			out_reg <= not(out_reg);
		end if;
	end if;
	end process;
	counter_process : process (clk)
	begin
	if (rising_edge(clk)) then
		if ((out_reg = '1') xor (signal_in = '1')) then
			if (ctr = maxctr) then
				ctr <= 0;
			else
				ctr <= ctr + 1;
			end if;
		else
			ctr <= 0;
		end if;
	end if;
	end process;
	counter_max_assignment : process (clk)
	begin
	if(out_reg = '0') then
		maxctr <= maxctr_up;
	else
		maxctr <= maxctr_down;
	end if;
	end process;
	signal_out <= out_reg;
end Behavioral;

content/hw2_q3_dut_tb.vhdl
library IEEE;
use IEEE.STD_LOGIC_1164.ALL;
entity hw2_q3_dut_tb is
end hw2_q3_dut_tb;
architecture Behavioral of hw2_q3_dut_tb is
    component dut
        Generic ( param_up : integer;
                  param_down : integer);
        Port ( signal_in : in  std_logic;
               clk : in  std_logic;
               signal_out : out  std_logic);
    end component;
    signal signal_in_tb : std_logic := '0';
    signal clk_tb : std_logic := '0';
    signal signal_out_tb : std_logic := '0';
    constant param_up_tb : integer := 2;
    constant param_down_tb : integer := 4;
begin
    dut_module: dut
            generic map(param_up => param_up_tb, param_down => param_down_tb)
            port map(signal_in => signal_in_tb, signal_out => signal_out_tb, clk => clk_tb);
    clk_process : process
    begin
        clk_tb <= '1';
        wait for 5 ns;
        clk_tb <= '0';
        wait for 5 ns;
    end process;
    sim_process : process
    begin
        assert false report "Running testbench" severity note;
    
        wait for 5 ns; -- offset everything to see rising edges clearly
        signal_in_tb <= '0';
        wait for 10 ns; -- 15ns
        assert signal_out_tb = '0' report "Should have gotten signal_out_tb = 0, but it didn't happen" severity error;
        signal_in_tb <= '1'; 
        wait for 10 ns; -- 25ns
        assert signal_out_tb = '0' report "Should have gotten signal_out_tb = 0, but it didn't happen" severity error;
        signal_in_tb <= '0'; 
        wait for 10 ns; -- 35ns 
        assert signal_out_tb = '0' report "Should have gotten signal_out_tb = 0, but it didn't happen" severity error;
        signal_in_tb <= '1';
        wait for 10 ns; -- 45ns
        assert signal_out_tb = '0' report "Should have gotten signal_out_tb = 0, but it didn't happen" severity error;
        wait for 20 ns; -- 65ns
        assert signal_out_tb = '1' report "Should have gotten signal_out_tb = 1, but it didn't happen" severity error;
        wait for 10 ns; -- 75ns
        signal_in_tb <= '0';
        wait for 10 ns; -- 125ns
        assert signal_out_tb = '1' report "Should have gotten signal_out_tb = 1, but it didn't happen" severity error;
        wait for 10 ns; -- 125ns
        assert signal_out_tb = '1' report "Should have gotten signal_out_tb = 1, but it didn't happen" severity error;
        wait for 10 ns; -- 125ns
        assert signal_out_tb = '1' report "Should have gotten signal_out_tb = 1, but it didn't happen" severity error;
        wait for 10 ns; -- 125ns
        assert signal_out_tb = '1' report "Should have gotten signal_out_tb = 1, but it didn't happen" severity error;
        wait for 10 ns; -- 125ns
        assert signal_out_tb = '0' report "Should have gotten signal_out_tb = 0, but it didn't happen" severity error;
        wait for 5 ns;  -- 130ns
        wait;
    end process;
end Behavioral;

content/hw2_q3_dut_tb_refout.vcd
$date
  Fri Nov 29 05:24:26 2024
$end
$version
  GHDL v0
$end
$timescale
  1 fs
$end
$scope module standard $end
$upscope $end
$scope module std_logic_1164 $end
$upscope $end
$scope module hw2_q3_dut_tb $end
$var reg 1 ! signal_in_tb $end
$var reg 1 " clk_tb $end
$var reg 1 # signal_out_tb $end
$scope module dut_module $end
$var reg 1 $ signal_in $end
$var reg 1 % clk $end
$var reg 1 & signal_out $end
$var integer 32 ' ctr $end
$var reg 1 ( out_reg $end
$var integer 32 ) maxctr $end
$upscope $end
$upscope $end
$enddefinitions $end
#0
0!
1"
0#
0$
1%
0&
b0 '
0(
b10 )
#5000000
0"
0%
#10000000
1"
1%
#15000000
1!
0"
1$
0%
#20000000
1"
1%
b1 '
#25000000
0!
0"
0$
0%
#30000000
1"
1%
b0 '
#35000000
1!
0"
1$
0%
#40000000
1"
1%
b1 '
#45000000
0"
0%
#50000000
1"
1%
b10 '
#55000000
0"
0%
#60000000
1"
1#
1%
1&
b0 '
1(
#65000000
0"
0%
b100 )
#70000000
1"
1%
#75000000
0!
0"
0$
0%
#80000000
1"
1%
b1 '
#85000000
0"
0%
#90000000
1"
1%
b10 '
#95000000
0"
0%
#100000000
1"
1%
b11 '
#105000000
0"
0%
#110000000
1"
1%
b100 '
#115000000
0"
0%
#120000000
1"
0#
1%
0&
b0 '
0(
#125000000
0"
0%
b10 )
